Metadata-Version: 2.1
Name: sterraxcyl
Version: 2.0
Summary: OSINT tool to work with follower/following list of instagram users.
Home-page: https://github.com/novitae/sterraxcyl
Author: novitae
License: GNU General Public License v3 (GPLv3)
Platform: UNKNOWN
Classifier: Programming Language :: Python :: 3.9
License-File: LICENCE
